dep_graph/__init__.py
dep_graph/__main__.py
dep_graph/exceptions.py
dep_graph/graph_resolver.py
dep_graph/helper/create_dummy_file.py
dep_graph/types.py
dep_graph/visualizations.py
dep_graph_hassan-1.0.1.dist-info/METADATA
dep_graph_hassan-1.0.1.dist-info/WHEEL
dep_graph_hassan-1.0.1.dist-info/RECORD
