Metadata-Version: 2.1
Name: dep-graph-hassan
Version: 1.0.1
Summary: Dependency Graph Resolution Package
Author: Muhammad Hassan Ahmed
Requires-Python: >=3.10,<4.0
Classifier: Programming Language :: Python :: 3
Classifier: Programming Language :: Python :: 3.10
Classifier: Programming Language :: Python :: 3.11
